htcutils/__init__.py
htcutils/__main__.py
htcutils/grid_error_logger.py
htcutils/mock_compute_engine_job_wrapper.py
htcutils/perf_tracker_firehose_connector.py
htcutils/perf_tracker_influxdb_connector.py
htcutils/performance_tracker.py
htcutils/state_table_common.py
htcutils/task_queue_common.py
htcutils/ttl_experation_generator.py
kbhtcutils-0.2.dist-info/LICENSE
kbhtcutils-0.2.dist-info/METADATA
kbhtcutils-0.2.dist-info/WHEEL
kbhtcutils-0.2.dist-info/top_level.txt
kbhtcutils-0.2.dist-info/RECORD
